{"S.No":122, "First_Name": "Tanvee", "Last_Name": "Alice", "source":"API", "description":"BPL", "input_timestamp":1774256609, "last_update_timestamp":1924256609, "country":"IND"}
{"S.No":123, "First_Name": "Sowjanya", "Last_Name": "Dinesh", "source":"REST", "description":"HRDA", "input_timestamp":1484256609, "last_update_timestamp":1094256609, "country":"US"}
{"S.No":124, "First_Name": "Umesh", "Last_Name": "Sreeni", "source":"ADLS", "description":"GEN1", "input_timestamp":1564256609, "last_update_timestamp":1524256609, "country":"CANADA"}
{"S.No":125, "First_Name": "Bharath", "Last_Name": "Sindu", "source":"Blob", "description":"exchange", "input_timestamp":1424256609, "last_update_timestamp":1724256609, "country":"US"}
{"S.No":126, "First_Name": "Saanvi", "Last_Name": "Suri", "source":"SQL", "description":"SERVER", "input_timestamp":1894256609, "last_update_timestamp":1394256609, "country":"SWEDEN"}
{"S.No":127, "First_Name": "Kavita", "Last_Name": "ELX", "source":"SUPPORT", "description":"ELT", "input_timestamp":1424256609, "last_update_timestamp":1874256609, "country":"UK"}
{"S.No":128, "First_Name": "Easwar", "Last_Name": "Firoj", "source":"AIRFLOW", "description":"ADF", "input_timestamp":1749256609, "last_update_timestamp":188256609, "country":"Norway"}
{"S.No":129, "First_Name": "Niroop", "Last_Name": "Girish", "source":"METADB", "description":"storage", "input_timestamp":1094256609, "last_update_timestamp":1724256609, "country":"US"}
{"S.No":130, "First_Name": "Danvika", "Last_Name": "Goalla", "source":"AWS", "description":"Glue", "input_timestamp":1924296909, "last_update_timestamp":1664256609, "country":"France"}
{"S.No":131, "First_Name": "Hitesh", "Last_Name": "Joy", "source":"Azure", "description":"Purview", "input_timestamp":1494256609, "last_update_timestamp":1924256609, "country":"Germany"}
{"S.No":132, "First_Name": "Danush", "Last_Name": "Jonna", "source":"databricks", "description":"ETL", "input_timestamp":13479256609, "last_update_timestamp":168256609, "country":"Denmark"}